<?xml version="1.0" encoding="utf-8"?>
<!DOCTYPE list SYSTEM "npc.dtd">
<list>
	<!-- Fake NPC -->
	<npc id="201" template_id="36071" name="FakeNPC" title="Test">
		<set name="aggroRange" value="0" />
		<set name="ai_type" value="CharacterAI" />
		<set name="baseAtkRange" value="40" />
		<set name="baseCON" value="43" />
		<set name="baseCritRate" value="40" />
		<set name="baseDEX" value="30" />
		<set name="baseHpMax" value="342.513" />
		<set name="baseHpRate" value="1" />
		<set name="baseHpReg" value="2.5" />
		<set name="baseINT" value="21" />
		<set name="baseMAtk" value="24" />
		<set name="baseMAtkSpd" value="500" />
		<set name="baseMDef" value="77" />
		<set name="baseMEN" value="20" />
		<set name="baseMpMax" value="192" />
		<set name="baseMpReg" value="1.2" />
		<set name="basePAtk" value="57" />
		<set name="basePAtkSpd" value="253" />
		<set name="basePDef" value="95" />
		<set name="baseRunSpd" value="120" />
		<set name="baseSTR" value="40" />
		<set name="baseShldDef" value="0" />
		<set name="baseShldRate" value="0" />
		<set name="baseWIT" value="20" />
		<set name="baseWalkSpd" value="30" />
		<set name="collision_height" value="72.5" />
		<set name="collision_radius" value="46.0" />
		<set name="level" value="20" />
		<set name="rewardExp" value="0" />
		<set name="rewardRp" value="0" />
		<set name="rewardSp" value="0" />
		<set name="shots" value="NONE" />
		<set name="texture" value="" />
		<set name="type" value="ClanPromotion" />
		<skills>
			<skill id="4416" level="19" />	<!--Others-->
		</skills>
		<attributes>
			<defence attribute="fire" value="20" />
			<defence attribute="water" value="20" />
			<defence attribute="wind" value="20" />
			<defence attribute="earth" value="20" />
			<defence attribute="holy" value="20" />
			<defence attribute="unholy" value="20" />
		</attributes>
	</npc>
	<npc id="399" template_id="32238" name="The Rock" title="Newbie Helper">
		<set name="aggroRange" value="0" />
		<set name="ai_type" value="CharacterAI" />
		<set name="baseAtkRange" value="40" />
		<set name="baseCON" value="43" />
		<set name="baseCritRate" value="40" />
		<set name="baseDEX" value="30" />
		<set name="baseHpMax" value="2444.468" />
		<set name="baseHpRate" value="1" />
		<set name="baseHpReg" value="7.5" />
		<set name="baseINT" value="21" />
		<set name="baseMAtk" value="780" />
		<set name="baseMAtkSpd" value="500" />
		<set name="baseMDef" value="382" />
		<set name="baseMEN" value="20" />
		<set name="baseMpMax" value="1345.8" />
		<set name="baseMpReg" value="2.7" />
		<set name="basePAtk" value="1303" />
		<set name="basePAtkSpd" value="253" />
		<set name="basePDef" value="471" />
		<set name="baseRunSpd" value="120" />
		<set name="baseSTR" value="40" />
		<set name="baseShldDef" value="0" />
		<set name="baseShldRate" value="0" />
		<set name="baseWIT" value="20" />
		<set name="baseWalkSpd" value="50" />
		<set name="collision_height" value="24.0" />
		<set name="collision_radius" value="7.0" />
		<set name="level" value="70" />
		<set name="rewardExp" value="0" />
		<set name="rewardRp" value="0" />
		<set name="rewardSp" value="0" />
		<set name="shots" value="NONE" />
		<set name="texture" value="" />
		<set name="type" value="Npc" />
		<skills>
			<skill id="4416" level="19" />	<!--Others-->
		</skills>
		<attributes>
			<defence attribute="fire" value="150" />
			<defence attribute="water" value="150" />
			<defence attribute="wind" value="150" />
			<defence attribute="earth" value="150" />
			<defence attribute="holy" value="150" />
			<defence attribute="unholy" value="150" />
		</attributes>
	</npc>
	<npc id="400" template_id="36071" name="The Statue" title="Clan Helper">
		<set name="aggroRange" value="0" />
		<set name="ai_type" value="CharacterAI" />
		<set name="baseAtkRange" value="40" />
		<set name="baseCON" value="43" />
		<set name="baseCritRate" value="40" />
		<set name="baseDEX" value="30" />
		<set name="baseHpMax" value="342.513" />
		<set name="baseHpRate" value="1" />
		<set name="baseHpReg" value="2.5" />
		<set name="baseINT" value="21" />
		<set name="baseMAtk" value="24" />
		<set name="baseMAtkSpd" value="500" />
		<set name="baseMDef" value="77" />
		<set name="baseMEN" value="20" />
		<set name="baseMpMax" value="192" />
		<set name="baseMpReg" value="1.2" />
		<set name="basePAtk" value="57" />
		<set name="basePAtkSpd" value="253" />
		<set name="basePDef" value="95" />
		<set name="baseRunSpd" value="120" />
		<set name="baseSTR" value="40" />
		<set name="baseShldDef" value="0" />
		<set name="baseShldRate" value="0" />
		<set name="baseWIT" value="20" />
		<set name="baseWalkSpd" value="30" />
		<set name="collision_height" value="72.5" />
		<set name="collision_radius" value="46.0" />
		<set name="level" value="20" />
		<set name="rewardExp" value="0" />
		<set name="rewardRp" value="0" />
		<set name="rewardSp" value="0" />
		<set name="shots" value="NONE" />
		<set name="texture" value="" />
		<set name="type" value="ClanPromotion" />
		<skills>
			<skill id="4416" level="19" />	<!--Others-->
		</skills>
		<attributes>
			<defence attribute="fire" value="20" />
			<defence attribute="water" value="20" />
			<defence attribute="wind" value="20" />
			<defence attribute="earth" value="20" />
			<defence attribute="holy" value="20" />
			<defence attribute="unholy" value="20" />
		</attributes>
	</npc>
	<npc id="401" template_id="4302" name="DumDum" title="Delevel Manager">
		<set name="aggroRange" value="0" />
		<set name="ai_type" value="CharacterAI" />
		<set name="baseAtkRange" value="40" />
		<set name="baseCON" value="43" />
		<set name="baseCritRate" value="40" />
		<set name="baseDEX" value="30" />
		<set name="baseHpMax" value="39.745" />
		<set name="baseHpRate" value="1" />
		<set name="baseHpReg" value="2" />
		<set name="baseINT" value="21" />
		<set name="baseMAtk" value="3" />
		<set name="baseMAtkSpd" value="500" />
		<set name="baseMDef" value="32" />
		<set name="baseMEN" value="20" />
		<set name="baseMpMax" value="40" />
		<set name="baseMpReg" value="0.9" />
		<set name="basePAtk" value="9" />
		<set name="basePAtkSpd" value="253" />
		<set name="basePDef" value="40" />
		<set name="baseRunSpd" value="180" />
		<set name="baseSTR" value="40" />
		<set name="baseShldDef" value="0" />
		<set name="baseShldRate" value="0" />
		<set name="baseWIT" value="20" />
		<set name="baseWalkSpd" value="110" />
		<set name="collision_height" value="16.7" />
		<set name="collision_radius" value="9.0" />
		<set name="level" value="1" />
		<set name="rewardExp" value="0" />
		<set name="rewardRp" value="0" />
		<set name="rewardSp" value="0" />
		<set name="shots" value="NONE" />
		<set name="texture" value="" />
		<set name="type" value="DelevelManager" />
		<attributes>
			<defence attribute="fire" value="20" />
			<defence attribute="water" value="20" />
			<defence attribute="wind" value="20" />
			<defence attribute="earth" value="20" />
			<defence attribute="holy" value="20" />
			<defence attribute="unholy" value="20" />
		</attributes>
	</npc>
	<npc id="402" template_id="32163" name="Global Gatekeeper" title="- L2WoA --">
		<set name="aggroRange" value="0" />
		<set name="ai_type" value="CharacterAI" />
		<set name="baseAtkRange" value="40" />
		<set name="baseCON" value="43" />
		<set name="baseCritRate" value="40" />
		<set name="baseDEX" value="30" />
		<set name="baseHpMax" value="2444.468" />
		<set name="baseHpRate" value="1" />
		<set name="baseHpReg" value="7.5" />
		<set name="baseINT" value="21" />
		<set name="baseMAtk" value="780" />
		<set name="baseMAtkSpd" value="500" />
		<set name="baseMDef" value="382" />
		<set name="baseMEN" value="20" />
		<set name="baseMpMax" value="1345.8" />
		<set name="baseMpReg" value="2.7" />
		<set name="basePAtk" value="1303" />
		<set name="basePAtkSpd" value="253" />
		<set name="basePDef" value="471" />
		<set name="baseRunSpd" value="180" />
		<set name="baseSTR" value="40" />
		<set name="baseShldDef" value="0" />
		<set name="baseShldRate" value="0" />
		<set name="baseWIT" value="20" />
		<set name="baseWalkSpd" value="110" />
		<set name="collision_height" value="23.0" />
		<set name="collision_radius" value="13.0" />
		<set name="level" value="85" />
		<set name="rewardExp" value="0" />
		<set name="rewardRp" value="0" />
		<set name="rewardSp" value="0" />
		<set name="shots" value="NONE" />
		<set name="texture" value="" />
		<set name="type" value="Merchant" />
		<skills>
			<skill id="4416" level="25" />	<!--Kamael-->
		</skills>
		<attributes>
			<defence attribute="fire" value="20" />
			<defence attribute="water" value="20" />
			<defence attribute="wind" value="20" />
			<defence attribute="earth" value="20" />
			<defence attribute="holy" value="20" />
			<defence attribute="unholy" value="20" />
		</attributes>
	</npc>
	<npc id="403" template_id="25544" name="Trader" title="-- L2WoA --">
		<set name="aggroRange" value="0" />
		<set name="ai_type" value="CharacterAI" />
		<set name="baseAtkRange" value="40" />
		<set name="baseCON" value="43" />
		<set name="baseCritRate" value="40" />
		<set name="baseDEX" value="30" />
		<set name="baseHpMax" value="2444.468" />
		<set name="baseHpRate" value="1" />
		<set name="baseHpReg" value="7.5" />
		<set name="baseINT" value="21" />
		<set name="baseMAtk" value="780" />
		<set name="baseMAtkSpd" value="500" />
		<set name="baseMDef" value="382" />
		<set name="baseMEN" value="20" />
		<set name="baseMpMax" value="1345.8" />
		<set name="baseMpReg" value="2.7" />
		<set name="basePAtk" value="1303" />
		<set name="basePAtkSpd" value="253" />
		<set name="basePDef" value="471" />
		<set name="baseRunSpd" value="180" />
		<set name="baseSTR" value="40" />
		<set name="baseShldDef" value="0" />
		<set name="baseShldRate" value="0" />
		<set name="baseWIT" value="20" />
		<set name="baseWalkSpd" value="110" />
		<set name="collision_height" value="41.0" />
		<set name="collision_radius" value="19.0" />
		<set name="level" value="85" />
		<set name="rewardExp" value="0" />
		<set name="rewardRp" value="0" />
		<set name="rewardSp" value="0" />
		<set name="shots" value="NONE" />
		<set name="texture" value="LineageNpc2.gracia_fsoldier_1hs" />
		<set name="type" value="Merchant" />
		<attributes>
			<defence attribute="fire" value="20" />
			<defence attribute="water" value="20" />
			<defence attribute="wind" value="20" />
			<defence attribute="earth" value="20" />
			<defence attribute="holy" value="20" />
			<defence attribute="unholy" value="20" />
		</attributes>
	</npc>
	<npc id="404" template_id="25286" name="Buffer" title="-- L2WoA --">
		<set name="aggroRange" value="0" />
		<set name="ai_type" value="CharacterAI" />
		<set name="baseAtkRange" value="40" />
		<set name="baseCON" value="43" />
		<set name="baseCritRate" value="40" />
		<set name="baseDEX" value="30" />
		<set name="baseHpMax" value="2444.468" />
		<set name="baseHpRate" value="1" />
		<set name="baseHpReg" value="7.5" />
		<set name="baseINT" value="21" />
		<set name="baseMAtk" value="780" />
		<set name="baseMAtkSpd" value="500" />
		<set name="baseMDef" value="382" />
		<set name="baseMEN" value="20" />
		<set name="baseMpMax" value="1345.8" />
		<set name="baseMpReg" value="2.7" />
		<set name="basePAtk" value="1303" />
		<set name="basePAtkSpd" value="253" />
		<set name="basePDef" value="471" />
		<set name="baseRunSpd" value="180" />
		<set name="baseSTR" value="40" />
		<set name="baseShldDef" value="0" />
		<set name="baseShldRate" value="0" />
		<set name="baseWIT" value="20" />
		<set name="baseWalkSpd" value="110" />
		<set name="collision_height" value="29.0" />
		<set name="collision_radius" value="15.5" />
		<set name="level" value="85" />
		<set name="rewardExp" value="0" />
		<set name="rewardRp" value="0" />
		<set name="rewardSp" value="0" />
		<set name="shots" value="NONE" />
		<set name="texture" value="" />
		<set name="type" value="Npc" />
		<attributes>
			<defence attribute="fire" value="20" />
			<defence attribute="water" value="20" />
			<defence attribute="wind" value="20" />
			<defence attribute="earth" value="20" />
			<defence attribute="holy" value="20" />
			<defence attribute="unholy" value="20" />
		</attributes>
	</npc>
	<npc id="405" template_id="25328" name="Auctioner" title="-- L2WoA --">
		<set name="aggroRange" value="0" />
		<set name="ai_type" value="CharacterAI" />
		<set name="baseAtkRange" value="40" />
		<set name="baseCON" value="43" />
		<set name="baseCritRate" value="40" />
		<set name="baseDEX" value="30" />
		<set name="baseHpMax" value="2444.468" />
		<set name="baseHpRate" value="1" />
		<set name="baseHpReg" value="7.5" />
		<set name="baseINT" value="21" />
		<set name="baseMAtk" value="780" />
		<set name="baseMAtkSpd" value="333" />
		<set name="baseMDef" value="382" />
		<set name="baseMEN" value="20" />
		<set name="baseMpMax" value="1345.8" />
		<set name="baseMpReg" value="2.7" />
		<set name="basePAtk" value="1303" />
		<set name="basePAtkSpd" value="253" />
		<set name="basePDef" value="471" />
		<set name="baseRunSpd" value="120" />
		<set name="baseSTR" value="40" />
		<set name="baseShldDef" value="0" />
		<set name="baseShldRate" value="0" />
		<set name="baseWIT" value="20" />
		<set name="baseWalkSpd" value="50" />
		<set name="castle_id" value="3" />
		<set name="collision_height" value="25.8" />
		<set name="collision_radius" value="7.5" />
		<set name="level" value="70" />
		<set name="rewardExp" value="0" />
		<set name="rewardRp" value="0" />
		<set name="rewardSp" value="0" />
		<set name="shots" value="NONE" />
		<set name="texture" value="" />
		<set name="type" value="Npc" />
		<attributes>
			<defence attribute="fire" value="150" />
			<defence attribute="water" value="150" />
			<defence attribute="wind" value="150" />
			<defence attribute="earth" value="150" />
			<defence attribute="holy" value="150" />
			<defence attribute="unholy" value="150" />
		</attributes>
	</npc>
	<npc id="406" template_id="32784" name="Raid Status" title="-- L2WoA --">
		<set name="aggroRange" value="0" />
		<set name="ai_type" value="CharacterAI" />
		<set name="baseAtkRange" value="40" />
		<set name="baseCON" value="43" />
		<set name="baseCritRate" value="40" />
		<set name="baseDEX" value="30" />
		<set name="baseHpMax" value="2880.376" />
		<set name="baseHpRate" value="1" />
		<set name="baseHpReg" value="8.5" />
		<set name="baseINT" value="21" />
		<set name="baseMAtk" value="1145" />
		<set name="baseMAtkSpd" value="333" />
		<set name="baseMDef" value="469" />
		<set name="baseMEN" value="20" />
		<set name="baseMpMax" value="1674.8" />
		<set name="baseMpReg" value="3" />
		<set name="basePAtk" value="1799" />
		<set name="basePAtkSpd" value="230" />
		<set name="basePDef" value="577" />
		<set name="baseRunSpd" value="114" />
		<set name="baseSTR" value="40" />
		<set name="baseShldDef" value="0" />
		<set name="baseShldRate" value="0" />
		<set name="baseWIT" value="20" />
		<set name="baseWalkSpd" value="22" />
		<set name="collision_height" value="23.0" />
		<set name="collision_radius" value="10.0" />
		<set name="level" value="80" />
		<set name="rewardExp" value="0" />
		<set name="rewardRp" value="0" />
		<set name="rewardSp" value="0" />
		<set name="shots" value="NONE" />
		<set name="texture" value="LineageNPC2.br_blessed_taiboy" />
		<set name="type" value="Npc" />
		<attributes>
			<defence attribute="fire" value="150" />
			<defence attribute="water" value="150" />
			<defence attribute="wind" value="150" />
			<defence attribute="earth" value="150" />
			<defence attribute="holy" value="150" />
			<defence attribute="unholy" value="150" />
		</attributes>
	</npc>
	<npc id="407" template_id="31691" name="Training Dummy" title="-- L2WoA --">
		<set name="aggroRange" value="0" />
		<set name="ai_type" value="CharacterAI" />
		<set name="baseAtkRange" value="40" />
		<set name="baseCON" value="43" />
		<set name="baseCritRate" value="40" />
		<set name="baseDEX" value="1" />
		<set name="baseHpMax" value="2444.468" />
		<set name="baseHpRate" value="1" />
		<set name="baseHpReg" value="7.5" />
		<set name="baseINT" value="21" />
		<set name="baseMAtk" value="780" />
		<set name="baseMAtkSpd" value="333" />
		<set name="baseMDef" value="2600" /> <!-- Or 2000 m.def and 2600 p.def, I dunno, bad at math. Check formulas to find the balancing point -->
		<set name="baseMEN" value="20" />
		<set name="baseMpMax" value="1345.8" />
		<set name="baseMpReg" value="2.7" />
		<set name="basePAtk" value="1303" />
		<set name="basePAtkSpd" value="253" />
		<set name="basePDef" value="2000" />
		<set name="baseRunSpd" value="120" />
		<set name="baseSTR" value="40" />
		<set name="baseShldDef" value="0" />
		<set name="baseShldRate" value="0" />
		<set name="baseWIT" value="20" />
		<set name="baseWalkSpd" value="50" />
		<set name="collision_height" value="22.0" />
		<set name="collision_radius" value="9.0" />
		<set name="level" value="70" />
		<set name="rewardExp" value="0" />
		<set name="rewardRp" value="0" />
		<set name="rewardSp" value="0" />
		<set name="shots" value="NONE" />
		<set name="texture" value="" />
		<set name="type" value="DPSTest" />
		<skills>
			<skill id="4416" level="19" />	<!--Others-->
		</skills>
		<attributes>
			<defence attribute="fire" value="20" />
			<defence attribute="water" value="20" />
			<defence attribute="wind" value="20" />
			<defence attribute="earth" value="20" />
			<defence attribute="holy" value="20" />
			<defence attribute="unholy" value="20" />
		</attributes>
	</npc>
	<npc id="10002" template_id="18715" name="GmShop" title="Free Shop">
		<set name="aggroRange" value="0" />
		<set name="ai_type" value="CharacterAI" />
		<set name="baseAtkRange" value="40" />
		<set name="baseCON" value="43" />
		<set name="baseCritRate" value="40" />
		<set name="baseDEX" value="30" />
		<set name="baseHpMax" value="2444.468" />
		<set name="baseHpRate" value="1" />
		<set name="baseHpReg" value="7.5" />
		<set name="baseINT" value="21" />
		<set name="baseMAtk" value="780" />
		<set name="baseMAtkSpd" value="500" />
		<set name="baseMDef" value="382" />
		<set name="baseMEN" value="20" />
		<set name="baseMpMax" value="1345.8" />
		<set name="baseMpReg" value="2.7" />
		<set name="basePAtk" value="1303" />
		<set name="basePAtkSpd" value="253" />
		<set name="basePDef" value="471" />
		<set name="baseRunSpd" value="180" />
		<set name="baseSTR" value="40" />
		<set name="baseShldDef" value="0" />
		<set name="baseShldRate" value="0" />
		<set name="baseWIT" value="20" />
		<set name="baseWalkSpd" value="110" />
		<set name="collision_height" value="40.0" />
		<set name="collision_radius" value="10.0" />
		<set name="level" value="85" />
		<set name="rewardExp" value="0" />
		<set name="rewardRp" value="0" />
		<set name="rewardSp" value="0" />
		<set name="shots" value="NONE" />
		<set name="texture" value="LineageNpc2.gracia_fsoldier_1hs" />
		<set name="type" value="Merchant" />
		<attributes>
			<defence attribute="fire" value="20" />
			<defence attribute="water" value="20" />
			<defence attribute="wind" value="20" />
			<defence attribute="earth" value="20" />
			<defence attribute="holy" value="20" />
			<defence attribute="unholy" value="20" />
		</attributes>
	</npc>
	<npc id="10003" template_id="31215" name="Event Manager" title="GM Hunter">
		<set name="aggroRange" value="0" />
		<set name="ai_type" value="CharacterAI" />
		<set name="baseAtkRange" value="40" />
		<set name="baseCON" value="43" />
		<set name="baseCritRate" value="40" />
		<set name="baseDEX" value="30" />
		<set name="baseHpMax" value="2444.468" />
		<set name="baseHpRate" value="1" />
		<set name="baseHpReg" value="7.5" />
		<set name="baseINT" value="21" />
		<set name="baseMAtk" value="780" />
		<set name="baseMAtkSpd" value="2530" />
		<set name="baseMDef" value="382" />
		<set name="baseMEN" value="20" />
		<set name="baseMpMax" value="1345.8" />
		<set name="baseMpReg" value="2.7" />
		<set name="basePAtk" value="1303" />
		<set name="basePAtkSpd" value="253" />
		<set name="basePDef" value="471" />
		<set name="baseRunSpd" value="120" />
		<set name="baseSTR" value="40" />
		<set name="baseShldDef" value="0" />
		<set name="baseShldRate" value="0" />
		<set name="baseWIT" value="20" />
		<set name="baseWalkSpd" value="48" />
		<set name="collision_height" value="15.0" />
		<set name="collision_radius" value="8.0" />
		<set name="level" value="70" />
		<set name="rewardExp" value="0" />
		<set name="rewardRp" value="0" />
		<set name="rewardSp" value="0" />
		<set name="shots" value="NONE" />
		<set name="texture" value="" />
		<set name="type" value="Npc" />
		<skills>
			<skill id="4416" level="7" />	<!--Spirits-->
		</skills>
		<attributes>
			<defence attribute="fire" value="150" />
			<defence attribute="water" value="150" />
			<defence attribute="wind" value="150" />
			<defence attribute="earth" value="150" />
			<defence attribute="holy" value="150" />
			<defence attribute="unholy" value="150" />
		</attributes>
	</npc>
	<npc id="10004" template_id="4303" name="Skooldy" title="Halloween Event">
		<set name="aggroRange" value="0" />
		<set name="ai_type" value="CharacterAI" />
		<set name="baseAtkRange" value="40" />
		<set name="baseCON" value="43" />
		<set name="baseCritRate" value="40" />
		<set name="baseDEX" value="30" />
		<set name="baseHpMax" value="2444.468" />
		<set name="baseHpRate" value="1" />
		<set name="baseHpReg" value="7.5" />
		<set name="baseINT" value="21" />
		<set name="baseMAtk" value="934" />
		<set name="baseMAtkSpd" value="500" />
		<set name="baseMDef" value="418" />
		<set name="baseMEN" value="20" />
		<set name="baseMpMax" value="1345.8" />
		<set name="baseMpReg" value="2.7" />
		<set name="basePAtk" value="1426" />
		<set name="basePAtkSpd" value="253" />
		<set name="basePDef" value="515" />
		<set name="baseRunSpd" value="180" />
		<set name="baseSTR" value="40" />
		<set name="baseShldDef" value="0" />
		<set name="baseShldRate" value="0" />
		<set name="baseWIT" value="20" />
		<set name="baseWalkSpd" value="110" />
		<set name="collision_height" value="23.0" />
		<set name="collision_radius" value="23.0" />
		<set name="level" value="85" />
		<set name="rewardExp" value="723" />
		<set name="rewardRp" value="0" />
		<set name="rewardSp" value="10" />
		<set name="shots" value="NONE" />
		<set name="texture" value="" />
		<set name="type" value="Npc" />
		<attributes>
			<defence attribute="fire" value="150" />
			<defence attribute="water" value="150" />
			<defence attribute="wind" value="150" />
			<defence attribute="earth" value="150" />
			<defence attribute="holy" value="150" />
			<defence attribute="unholy" value="150" />
		</attributes>
	</npc>
	<npc id="10005" template_id="4303" name="DummyNpc" title="">
		<set name="aggroRange" value="0" />
		<set name="ai_type" value="CharacterAI" />
		<set name="baseAtkRange" value="40" />
		<set name="baseCON" value="43" />
		<set name="baseCritRate" value="40" />
		<set name="baseDEX" value="30" />
		<set name="baseHpMax" value="2444.468" />
		<set name="baseHpRate" value="1" />
		<set name="baseHpReg" value="7.5" />
		<set name="baseINT" value="21" />
		<set name="baseMAtk" value="934" />
		<set name="baseMAtkSpd" value="500" />
		<set name="baseMDef" value="418" />
		<set name="baseMEN" value="20" />
		<set name="baseMpMax" value="1345.8" />
		<set name="baseMpReg" value="2.7" />
		<set name="basePAtk" value="1426" />
		<set name="basePAtkSpd" value="253" />
		<set name="basePDef" value="515" />
		<set name="baseRunSpd" value="180" />
		<set name="baseSTR" value="40" />
		<set name="baseShldDef" value="0" />
		<set name="baseShldRate" value="0" />
		<set name="baseWIT" value="20" />
		<set name="baseWalkSpd" value="110" />
		<set name="collision_height" value="23.0" />
		<set name="collision_radius" value="23.0" />
		<set name="level" value="85" />
		<set name="rewardExp" value="723" />
		<set name="rewardRp" value="0" />
		<set name="rewardSp" value="10" />
		<set name="shots" value="NONE" />
		<set name="texture" value="" />
		<set name="type" value="Npc" />
		<attributes>
			<defence attribute="fire" value="150" />
			<defence attribute="water" value="150" />
			<defence attribute="wind" value="150" />
			<defence attribute="earth" value="150" />
			<defence attribute="holy" value="150" />
			<defence attribute="unholy" value="150" />
		</attributes>
	</npc>
	<!-- DO NOT SPAWN THIS NPC -->
	<npc id="603" name="" title="">
		<set name="aggroRange" value="0" />
		<set name="ai_type" value="CharacterAI" />
		<set name="baseAtkRange" value="40" />
		<set name="baseCON" value="43" />
		<set name="baseCritRate" value="40" />
		<set name="baseDEX" value="30" />
		<set name="baseHpMax" value="1673.055" />
		<set name="baseHpRate" value="1" />
		<set name="baseHpReg" value="6.5" />
		<set name="baseINT" value="21" />
		<set name="baseMAtk" value="361" />
		<set name="baseMAtkSpd" value="500" />
		<set name="baseMDef" value="262" />
		<set name="baseMEN" value="25" />
		<set name="baseMpMax" value="889.8" />
		<set name="baseMpReg" value="2.4" />
		<set name="basePAtk" value="665" />
		<set name="basePAtkSpd" value="253" />
		<set name="basePDef" value="322" />
		<set name="baseRunSpd" value="120" />
		<set name="baseSTR" value="40" />
		<set name="baseShldDef" value="0" />
		<set name="baseShldRate" value="0" />
		<set name="baseWIT" value="20" />
		<set name="baseWalkSpd" value="80" />
		<set name="collision_height" value="36.0" />
		<set name="collision_radius" value="90.0" />
		<set name="level" value="55" />
		<set name="rewardExp" value="0" />
		<set name="rewardRp" value="0" />
		<set name="rewardSp" value="0" />
		<set name="shots" value="NONE" />
		<set name="texture" value="" />
		<set name="type" value="Visual" />
		<skills>
			<skill id="4416" level="4" />	<!--Animals-->
		</skills>
		<attributes>
			<defence attribute="fire" value="20" />
			<defence attribute="water" value="20" />
			<defence attribute="wind" value="20" />
			<defence attribute="earth" value="20" />
			<defence attribute="holy" value="20" />
			<defence attribute="unholy" value="20" />
		</attributes>
	</npc>
	<npc id="604" template_id="18715" name="Teleport" title="Wyvern">
		<set name="aggroRange" value="0" />
		<set name="ai_type" value="CharacterAI" />
		<set name="baseAtkRange" value="40" />
		<set name="baseCON" value="43" />
		<set name="baseCritRate" value="40" />
		<set name="baseDEX" value="30" />
		<set name="baseHpMax" value="2444.468" />
		<set name="baseHpRate" value="1" />
		<set name="baseHpReg" value="7.5" />
		<set name="baseINT" value="21" />
		<set name="baseMAtk" value="780" />
		<set name="baseMAtkSpd" value="500" />
		<set name="baseMDef" value="382" />
		<set name="baseMEN" value="20" />
		<set name="baseMpMax" value="1345.8" />
		<set name="baseMpReg" value="2.7" />
		<set name="basePAtk" value="1303" />
		<set name="basePAtkSpd" value="253" />
		<set name="basePDef" value="471" />
		<set name="baseRunSpd" value="180" />
		<set name="baseSTR" value="40" />
		<set name="baseShldDef" value="0" />
		<set name="baseShldRate" value="0" />
		<set name="baseWIT" value="20" />
		<set name="baseWalkSpd" value="110" />
		<set name="collision_height" value="40.0" />
		<set name="collision_radius" value="10.0" />
		<set name="level" value="85" />
		<set name="rewardExp" value="0" />
		<set name="rewardRp" value="0" />
		<set name="rewardSp" value="0" />
		<set name="shots" value="NONE" />
		<set name="texture" value="LineageNpc2.gracia_fsoldier_1hs" />
		<set name="type" value="Npc" />
		<attributes>
			<defence attribute="fire" value="20" />
			<defence attribute="water" value="20" />
			<defence attribute="wind" value="20" />
			<defence attribute="earth" value="20" />
			<defence attribute="holy" value="20" />
			<defence attribute="unholy" value="20" />
		</attributes>
	</npc>
	<npc id="700" template_id="13086" name="BETA" title="Shop">
		<set name="aggroRange" value="0" />
		<set name="ai_type" value="CharacterAI" />
		<set name="baseAtkRange" value="40" />
		<set name="baseCON" value="43" />
		<set name="baseCritRate" value="40" />
		<set name="baseDEX" value="30" />
		<set name="baseHpMax" value="1673.055" />
		<set name="baseHpRate" value="1" />
		<set name="baseHpReg" value="6.5" />
		<set name="baseINT" value="21" />
		<set name="baseMAtk" value="361" />
		<set name="baseMAtkSpd" value="500" />
		<set name="baseMDef" value="262" />
		<set name="baseMEN" value="25" />
		<set name="baseMpMax" value="889.8" />
		<set name="baseMpReg" value="2.4" />
		<set name="basePAtk" value="665" />
		<set name="basePAtkSpd" value="253" />
		<set name="basePDef" value="322" />
		<set name="baseRunSpd" value="120" />
		<set name="baseSTR" value="40" />
		<set name="baseShldDef" value="0" />
		<set name="baseShldRate" value="0" />
		<set name="baseWIT" value="20" />
		<set name="baseWalkSpd" value="30" />
		<set name="collision_height" value="31.57" />
		<set name="collision_radius" value="12.0" />
		<set name="level" value="55" />
		<set name="rewardExp" value="0" />
		<set name="rewardRp" value="0" />
		<set name="rewardSp" value="0" />
		<set name="shots" value="NONE" />
		<set name="texture" value="" />
		<set name="type" value="Npc" />
		<equip>
			<rhand item_id="8190" />	<!--Demonic Sword Zariche-->
		</equip>
		<attributes>
			<defence attribute="fire" value="20" />
			<defence attribute="water" value="20" />
			<defence attribute="wind" value="20" />
			<defence attribute="earth" value="20" />
			<defence attribute="holy" value="20" />
			<defence attribute="unholy" value="20" />
		</attributes>
	</npc>
	<npc id="800" template_id="30627" name="Tree" title="">
        <set name="aggroRange" value="0"/>
        <set name="ai_type" value="CharacterAI"/>
        <set name="baseAtkRange" value="40"/>
        <set name="baseCON" value="43"/>
        <set name="baseCritRate" value="40"/>
        <set name="baseDEX" value="30"/>
        <set name="baseHpMax" value="2444.468"/>
        <set name="baseHpRate" value="1"/>
        <set name="baseHpReg" value="7.5"/>
        <set name="baseINT" value="21"/>
        <set name="baseMAtk" value="780"/>
        <set name="baseMAtkSpd" value="500"/>
        <set name="baseMDef" value="382"/>
        <set name="baseMEN" value="20"/>
        <set name="baseMpMax" value="1345.8"/>
        <set name="baseMpReg" value="2.7"/>
        <set name="basePAtk" value="1303"/>
        <set name="basePAtkSpd" value="253"/>
        <set name="basePDef" value="471"/>
        <set name="baseRunSpd" value="120"/>
        <set name="baseSTR" value="40"/>
        <set name="baseShldDef" value="0"/>
        <set name="baseShldRate" value="0"/>
        <set name="baseWIT" value="20"/>
        <set name="baseWalkSpd" value="50"/>
        <set name="castle_id" value="2"/>
        <set name="collision_height" value="90.0"/>
        <set name="collision_radius" value="35.0"/>
        <set name="level" value="70"/>
        <set name="isAgro" value="0"/>
        <set name="rewardExp" value="0"/>
        <set name="rewardRp" value="0"/>
        <set name="rewardSp" value="0"/>
        <set name="shots" value="NONE"/>
        <set name="texture" value=""/>
        <set name="type" value="Npc"/>
        <ai_params>
            <set name="TargetEnabled" value="false"/>
            <set name="showName" value="false"/>
        </ai_params>
        <skills>
        </skills>
        <attributes>
            <defence attribute="fire" value="150"/>
            <defence attribute="water" value="150"/>
            <defence attribute="wind" value="150"/>
            <defence attribute="earth" value="150"/>
            <defence attribute="holy" value="150"/>
            <defence attribute="unholy" value="150"/>
        </attributes>
    </npc>
    <npc id="802" template_id="32792" name="Izabella" title="GateKeeper">
        <set name="aggroRange" value="0"/>
        <set name="ai_type" value="CharacterAI"/>
        <set name="baseAtkRange" value="40"/>
        <set name="baseCON" value="43"/>
        <set name="baseCritRate" value="40"/>
        <set name="baseDEX" value="30"/>
        <set name="baseHpMax" value="680"/>
        <set name="baseHpRate" value="1"/>
        <set name="baseHpReg" value="0"/>
        <set name="baseINT" value="21"/>
        <set name="baseMAtk" value="11"/>
        <set name="baseMAtkSpd" value="253"/>
        <set name="baseMDef" value="375180"/>
        <set name="baseMEN" value="20"/>
        <set name="baseMpMax" value="2000"/>
        <set name="baseMpReg" value="0.9"/>
        <set name="basePAtk" value="17"/>
        <set name="basePAtkSpd" value="253"/>
        <set name="basePDef" value="101400"/>
        <set name="baseRunSpd" value="120"/>
        <set name="baseSTR" value="40"/>
        <set name="baseShldDef" value="0"/>
        <set name="baseShldRate" value="0"/>
        <set name="baseWIT" value="20"/>
        <set name="baseWalkSpd" value="30"/>
        <set name="collision_height" value="22.0"/>
        <set name="collision_radius" value="11.0"/>
        <set name="level" value="80"/>
        <set name="isAgro" value="0"/>
        <set name="rewardExp" value="0"/>
        <set name="rewardRp" value="0"/>
        <set name="rewardSp" value="0"/>
        <set name="shots" value="NONE"/>
        <set name="texture" value=""/>
        <set name="type" value="Npc"/>
        <attributes>
            <defence attribute="fire" value="20"/>
            <defence attribute="water" value="20"/>
            <defence attribute="wind" value="20"/>
            <defence attribute="earth" value="20"/>
            <defence attribute="holy" value="20"/>
            <defence attribute="unholy" value="20"/>
        </attributes>
    </npc>
    <npc id="803" template_id="110" name="GvG" title="Statue of Legends">
		<set name="aggroRange" value="0" />
		<set name="ai_type" value="CharacterAI" />
		<set name="baseAtkRange" value="40" />
		<set name="baseCON" value="43" />
		<set name="baseCritRate" value="40" />
		<set name="baseDEX" value="30" />
		<set name="baseHpMax" value="2444.468" />
		<set name="baseHpRate" value="1" />
		<set name="baseHpReg" value="7.5" />
		<set name="baseINT" value="21" />
		<set name="baseMAtk" value="780" />
		<set name="baseMAtkSpd" value="500" />
		<set name="baseMDef" value="382" />
		<set name="baseMEN" value="10" />
		<set name="baseMpMax" value="1345.8" />
		<set name="baseMpReg" value="2.7" />
		<set name="basePAtk" value="1303" />
		<set name="basePAtkSpd" value="253" />
		<set name="basePDef" value="471" />
		<set name="baseRunSpd" value="180" />
		<set name="baseSTR" value="40" />
		<set name="baseShldDef" value="0" />
		<set name="baseShldRate" value="0" />
		<set name="baseWIT" value="20" />
		<set name="baseWalkSpd" value="110" />
		<set name="collision_height" value="35.0" />
		<set name="collision_radius" value="50.0" />
		<set name="level" value="70" />
		<set name="rewardExp" value="490" />
		<set name="rewardRp" value="0" />
		<set name="rewardSp" value="10" />
		<set name="shots" value="NONE" />
		<set name="texture" value="" />
		<set name="type" value="Npc" />
		<attributes>
			<defence attribute="fire" value="20" />
			<defence attribute="water" value="20" />
			<defence attribute="wind" value="20" />
			<defence attribute="earth" value="20" />
			<defence attribute="holy" value="20" />
			<defence attribute="unholy" value="20" />
		</attributes>
	</npc>
	<npc id="900" template_id="143" name="Totem of Body" title="">
		<set name="aggroRange" value="0" />
		<set name="ai_type" value="CharacterAI" />
		<set name="baseAtkRange" value="40" />
		<set name="baseCON" value="43" />
		<set name="baseCritRate" value="40" />
		<set name="baseDEX" value="30" />
		<set name="baseHpMax" value="2880.376" />
		<set name="baseHpRate" value="1" />
		<set name="baseHpReg" value="8.5" />
		<set name="baseINT" value="21" />
		<set name="baseMAtk" value="1145" />
		<set name="baseMAtkSpd" value="253" />
		<set name="baseMDef" value="469" />
		<set name="baseMEN" value="20" />
		<set name="baseMpMax" value="1674.8" />
		<set name="baseMpReg" value="3" />
		<set name="basePAtk" value="1799" />
		<set name="basePAtkSpd" value="253" />
		<set name="basePDef" value="577" />
		<set name="baseRunSpd" value="120" />
		<set name="baseSTR" value="40" />
		<set name="baseShldDef" value="0" />
		<set name="baseShldRate" value="0" />
		<set name="baseWIT" value="20" />
		<set name="baseWalkSpd" value="30" />
		<set name="collision_height" value="15.0" />
		<set name="collision_radius" value="7.0" />
		<set name="level" value="80" />
		<set name="rewardExp" value="0" />
		<set name="rewardRp" value="0" />
		<set name="rewardSp" value="0" />
		<set name="shots" value="NONE" />
		<set name="texture" value="" />
		<set name="type" value="Npc" />
		<ai_params>
			<set name="TargetEnabled" value="false" />
			<set name="showName" value="false" />
		</ai_params>
		<attributes>
			<defence attribute="fire" value="20" />
			<defence attribute="water" value="20" />
			<defence attribute="wind" value="20" />
			<defence attribute="earth" value="20" />
			<defence attribute="holy" value="20" />
			<defence attribute="unholy" value="20" />
		</attributes>
	</npc>
	<npc id="901" template_id="144" name="Totem of Spirit" title="">
		<set name="aggroRange" value="0" />
		<set name="ai_type" value="CharacterAI" />
		<set name="baseAtkRange" value="40" />
		<set name="baseCON" value="43" />
		<set name="baseCritRate" value="40" />
		<set name="baseDEX" value="30" />
		<set name="baseHpMax" value="2880.376" />
		<set name="baseHpRate" value="1" />
		<set name="baseHpReg" value="8.5" />
		<set name="baseINT" value="21" />
		<set name="baseMAtk" value="1145" />
		<set name="baseMAtkSpd" value="253" />
		<set name="baseMDef" value="469" />
		<set name="baseMEN" value="20" />
		<set name="baseMpMax" value="1674.8" />
		<set name="baseMpReg" value="3" />
		<set name="basePAtk" value="1799" />
		<set name="basePAtkSpd" value="253" />
		<set name="basePDef" value="577" />
		<set name="baseRunSpd" value="120" />
		<set name="baseSTR" value="40" />
		<set name="baseShldDef" value="0" />
		<set name="baseShldRate" value="0" />
		<set name="baseWIT" value="20" />
		<set name="baseWalkSpd" value="30" />
		<set name="collision_height" value="15.0" />
		<set name="collision_radius" value="7.0" />
		<set name="level" value="80" />
		<set name="rewardExp" value="0" />
		<set name="rewardRp" value="0" />
		<set name="rewardSp" value="0" />
		<set name="shots" value="NONE" />
		<set name="texture" value="" />
		<set name="type" value="Npc" />
		<ai_params>
			<set name="TargetEnabled" value="false" />
			<set name="showName" value="false" />
		</ai_params>
		<attributes>
			<defence attribute="fire" value="20" />
			<defence attribute="water" value="20" />
			<defence attribute="wind" value="20" />
			<defence attribute="earth" value="20" />
			<defence attribute="holy" value="20" />
			<defence attribute="unholy" value="20" />
		</attributes>
	</npc>
	<npc id="902" template_id="145" name="Totem of Bravery" title="">
		<set name="aggroRange" value="0" />
		<set name="ai_type" value="CharacterAI" />
		<set name="baseAtkRange" value="40" />
		<set name="baseCON" value="43" />
		<set name="baseCritRate" value="40" />
		<set name="baseDEX" value="30" />
		<set name="baseHpMax" value="2880.376" />
		<set name="baseHpRate" value="1" />
		<set name="baseHpReg" value="8.5" />
		<set name="baseINT" value="21" />
		<set name="baseMAtk" value="1145" />
		<set name="baseMAtkSpd" value="253" />
		<set name="baseMDef" value="469" />
		<set name="baseMEN" value="20" />
		<set name="baseMpMax" value="1674.8" />
		<set name="baseMpReg" value="3" />
		<set name="basePAtk" value="1799" />
		<set name="basePAtkSpd" value="253" />
		<set name="basePDef" value="577" />
		<set name="baseRunSpd" value="120" />
		<set name="baseSTR" value="40" />
		<set name="baseShldDef" value="0" />
		<set name="baseShldRate" value="0" />
		<set name="baseWIT" value="20" />
		<set name="baseWalkSpd" value="30" />
		<set name="collision_height" value="15.0" />
		<set name="collision_radius" value="7.0" />
		<set name="level" value="80" />
		<set name="rewardExp" value="0" />
		<set name="rewardRp" value="0" />
		<set name="rewardSp" value="0" />
		<set name="shots" value="NONE" />
		<set name="texture" value="" />
		<set name="type" value="Npc" />
		<ai_params>
			<set name="TargetEnabled" value="false" />
			<set name="showName" value="false" />
		</ai_params>
		<attributes>
			<defence attribute="fire" value="20" />
			<defence attribute="water" value="20" />
			<defence attribute="wind" value="20" />
			<defence attribute="earth" value="20" />
			<defence attribute="holy" value="20" />
			<defence attribute="unholy" value="20" />
		</attributes>
	</npc>
	<npc id="903" template_id="146" name="Totem of Fortitude" title="">
		<set name="aggroRange" value="0" />
		<set name="ai_type" value="CharacterAI" />
		<set name="baseAtkRange" value="40" />
		<set name="baseCON" value="43" />
		<set name="baseCritRate" value="40" />
		<set name="baseDEX" value="30" />
		<set name="baseHpMax" value="2880.376" />
		<set name="baseHpRate" value="1" />
		<set name="baseHpReg" value="8.5" />
		<set name="baseINT" value="21" />
		<set name="baseMAtk" value="1145" />
		<set name="baseMAtkSpd" value="253" />
		<set name="baseMDef" value="469" />
		<set name="baseMEN" value="20" />
		<set name="baseMpMax" value="1674.8" />
		<set name="baseMpReg" value="3" />
		<set name="basePAtk" value="1799" />
		<set name="basePAtkSpd" value="253" />
		<set name="basePDef" value="577" />
		<set name="baseRunSpd" value="120" />
		<set name="baseSTR" value="40" />
		<set name="baseShldDef" value="0" />
		<set name="baseShldRate" value="0" />
		<set name="baseWIT" value="20" />
		<set name="baseWalkSpd" value="30" />
		<set name="collision_height" value="15.0" />
		<set name="collision_radius" value="7.0" />
		<set name="level" value="80" />
		<set name="rewardExp" value="0" />
		<set name="rewardRp" value="0" />
		<set name="rewardSp" value="0" />
		<set name="shots" value="NONE" />
		<set name="texture" value="" />
		<set name="type" value="Npc" />
		<ai_params>
			<set name="TargetEnabled" value="false" />
			<set name="showName" value="false" />
		</ai_params>
		<attributes>
			<defence attribute="fire" value="20" />
			<defence attribute="water" value="20" />
			<defence attribute="wind" value="20" />
			<defence attribute="earth" value="20" />
			<defence attribute="holy" value="20" />
			<defence attribute="unholy" value="20" />
		</attributes>
	</npc>
</list>